LICENSE
MANIFEST.in
README.md
setup.py
libpytthonpro/__init__.py
libpytthonpro/github_api.py
libpytthonpro.egg-info/PKG-INFO
libpytthonpro.egg-info/SOURCES.txt
libpytthonpro.egg-info/dependency_links.txt
libpytthonpro.egg-info/not-zip-safe
libpytthonpro.egg-info/requires.txt
libpytthonpro.egg-info/top_level.txt